{
  "en-US": [
    {
      "title": "Taiwan Open Government Report Release Forum / SotM Taiwan Summit",
      "date": "Sep. 10th",
      "venue": "Taipei Teacher's Hostel",
      "address": "No.15, Nanhai Rd., Zhongzheng Dist., Taipei City 100, Taiwan",
      "pic": [],
      "website": "www.tth.url.tw",
      "link": "http://www.tth.url.tw/",
      "googlemap_emb": "https://www.google.com/maps/embed?pb=!1m18!1m12!1m3!1d3615.053828682036!2d121.5130531508528!3d25.032247244436466!2m3!1f0!2f0!3f0!3m2!1i1024!2i768!4f13.1!3m3!1m2!1s0x3442a998b148737f%3A0x93dfe8acc87177f7!2z6Ie65YyX5pWZ5bir5pyD6aSo!5e0!3m2!1szh-TW!2stw!4v1504171969691",
      "googlemap_link": "https://www.google.com.tw/maps/place/%E8%87%BA%E5%8C%97%E6%95%99%E5%B8%AB%E6%9C%83%E9%A4%A8/@25.0322472,121.5130532,17z/data=!3m1!4b1!4m5!3m4!1s0x3442a998b148737f:0x93dfe8acc87177f7!8m2!3d25.0322424!4d121.5152472",
      "howtogo": [
          {
            "title":"MRT",
            "godesc": ["The closest metro is “Chiang Kai-shek Memorial Station” station (Red line and Green Line of Metro Taipei) exit 1."]
          }
      ],
      "detail": ""
    },
    {
      "title": "Social Event & g0v Civic Tech Grant DEMO Party",
      "date": "Sep. 11th",
      "venue": "Google Taipei, Taipei 101",
      "address": "75F, No.7, Sec. 5, Xinyi Rd., Xinyi Dist., Taipei City, Taiwan.",
      "pic": ["Taipei_101.jpg"],
      "website": "www.taipei-101.com.tw",
      "link": "http://www.taipei-101.com.tw/en/index.aspx",
      "googlemap_emb": "https://www.google.com/maps/embed?pb=!1m18!1m12!1m3!1d3615.005038298767!2d121.56232116500627!3d25.03390308397241!2m3!1f0!2f0!3f0!3m2!1i1024!2i768!4f13.1!3m3!1m2!1s0x3442abb6da9c9e1f%3A0x1206bcf082fd10a6!2zMTEw5Y-w5YyX5biC5L-h576p5Y2A5L-h576p6Lev5LqU5q61N-iZn-WPsOWMlzEwMQ!5e0!3m2!1szh-TW!2stw!4v1504003750468",
      "googlemap_link": "https://www.google.com.tw/maps/place/110%E5%8F%B0%E5%8C%97%E5%B8%82%E4%BF%A1%E7%BE%A9%E5%8D%80%E4%BF%A1%E7%BE%A9%E8%B7%AF%E4%BA%94%E6%AE%B57%E8%99%9F%E5%8F%B0%E5%8C%97101/data=!4m2!3m1!1s0x3442abb6da9c9e1f:0x1206bcf082fd10a6?sa=X&ved=0ahUKEwj30vL_ovzVAhXIUbwKHRMGCssQ8gEIJDAA",
      "howtogo": [
          {
            "title":"MRT",
            "godesc": ["The closest metro is “Taipei 101/World Trade Center“ station (red line of Metro Taipei) Exit 4."]
          },
          {
            "title":"Entry Gate",
            "godesc": ["The gate to Google Taipei office is on the Xinyi Road, beyond the “LOVE” statues."]
          }
      ],
      "detail": ""
    },
    {
      "title": "g0v 5th Anniversary Hackathon",
      "date": "Sep. 16th",
      "venue": "TAF innovation base - Restaurant (聯合餐廳)",
      "address": "No.177, Sec. 1, Jianguo S. Rd., Da’an Dist., Taipei City 106, Taiwan",
      "pic": ["TAF_base.jpg"],
      "website": "taiwanairforce.org",
      "link": "http://taiwanairforce.org/",
      "googlemap_emb": "https://www.google.com/maps/embed?pb=!1m18!1m12!1m3!1d3614.806031414264!2d121.5358033150064!3d25.0406558839692!2m3!1f0!2f0!3f0!3m2!1i1024!2i768!4f13.1!3m3!1m2!1s0x3442abd7cc8d7927%3A0xd637c365adc4884a!2z56m657i95Ym15paw5Z-65Zyw77yM6IGv5ZCI6aSQ5buz!5e0!3m2!1szh-TW!2stw!4v1504003857490",
      "googlemap_link": "https://www.google.com.tw/maps/place/%E7%A9%BA%E7%B8%BD%E5%89%B5%E6%96%B0%E5%9F%BA%E5%9C%B0%EF%BC%8C%E8%81%AF%E5%90%88%E9%A4%90%E5%BB%B3/@25.0406559,121.5358033,17z/data=!4m13!1m7!3m6!1s0x3442abd7cc8d7927:0xd22099cc815aa168!2zMTA25Y-w5YyX5biC5aSn5a6J5Y2A5bu65ZyL5Y2X6Lev5LiA5q61MTc36Jmf!3b1!8m2!3d25.0406559!4d121.537992!3m4!1s0x3442abd7cc8d7927:0xd637c365adc4884a!8m2!3d25.0406559!4d121.537992",
      "howtogo": [
          {
            "title":"MRT",
            "godesc": ["closest metro is “Zhongxiao Xinsheng“ station (Blue line of Metro Taipei) Exit 3."]
          }
      ],
      "detail": ""
    }
  ],
  "zh-TW": [
    {
      "title": "地點",
      "date": "",
      "venue": "",
      "address": "",
      "website": "",
      "howtogo": [
          {
            "title":"MRT",
            "godesc": [""]
          }
      ],
      "detail": "地點"
    }
  ]
}

